topsis/__init__.py
topsis/__main__.py
Topsis_Kaustubh_102203194-1.0.0.dist-info/LICENSE
Topsis_Kaustubh_102203194-1.0.0.dist-info/METADATA
Topsis_Kaustubh_102203194-1.0.0.dist-info/WHEEL
Topsis_Kaustubh_102203194-1.0.0.dist-info/entry_points.txt
Topsis_Kaustubh_102203194-1.0.0.dist-info/top_level.txt
Topsis_Kaustubh_102203194-1.0.0.dist-info/RECORD
